health_service/__init__.py
health_service/admin.py
health_service/models.py
health_service/tests.py
health_service/urls.py
health_service/migrations/0001_initial.py
health_service/migrations/0002_auto_20170320_1024.py
health_service/migrations/0003_update_area_related_name.py
health_service/migrations/0004_catchment_areas_is_blankable.py
health_service/migrations/__init__.py
health_service/templates/django_extensions/widgets/foreignkey_searchinput.html
health_service-1.3.4.dist-info/METADATA
health_service-1.3.4.dist-info/RECORD
health_service-1.3.4.dist-info/WHEEL
health_service-1.3.4.dist-info/top_level.txt
