Metadata-Version: 2.1
Name: health-service
Version: 1.3.4
Summary: Health Service model for Catalpa's projects.
Home-page: http://www.github.com/catalpainternational/health_service
Author: Anders Hofstee
Author-email: a.hofstee@catalpainternational.org
License: BSD
Platform: UNKNOWN
Classifier: Development Status :: 5 - Production/Stable
Classifier: Topic :: Utilities
Classifier: License :: OSI Approved :: BSD License
